reader/__init__.py
reader/__main__.py
reader/feed.py
reader/viewer.py
rinki_reader-1.0.0.dist-info/METADATA
rinki_reader-1.0.0.dist-info/WHEEL
rinki_reader-1.0.0.dist-info/entry_points.txt
rinki_reader-1.0.0.dist-info/top_level.txt
rinki_reader-1.0.0.dist-info/RECORD
